{
  "schemaVersion": 1,
  "id": "neptune",
  "version": "${version}",
  "name": "Neptune",
  "description": "stay with me, as we cross the empty skies",
  "authors": [
    "heedi"
  ],
  "contact": {},
  "license": "unlicense",
  "environment": "client",
  "entrypoints": {
    "client": [
      "me.neptune.Neptune"
    ],
    "main": [
      "me.neptune.Neptune"
    ]
  },
  "mixins": [
    "neptune.mixins.json"
  ],
  "depends": {
    "fabricloader": ">=${loader_version}",
    "fabric": "*",
    "minecraft": "${minecraft_version}"
  }
}
